TurboEZ/__init__.py
TurboEZ/validate_drive_.py
TurboEZ/vtg_ezztp_inertia_register_tbm_.py
TurboEZ/z_core.py
TurboEZ/z_main.py
TurboEZ-0.3.9.dist-info/LICENSE.txt
TurboEZ-0.3.9.dist-info/METADATA
TurboEZ-0.3.9.dist-info/WHEEL
TurboEZ-0.3.9.dist-info/top_level.txt
TurboEZ-0.3.9.dist-info/RECORD
