Metadata-Version: 2.1
Name: TurboEZ
Version: 0.3.9
Summary: A Tool for Ping of Hosts
Home-page: https://github.com/chenchaotsun/scripts
Author: Chaoqun Chen
Author-email: chen.chaoqun.ext@99cloud.net
License: GNU General Public License v3.0
Project-URL: Bug Tracker, https://github.com/pypa/sampleproject/issues
Keywords: ztp
Platform: UNKNOWN
Classifier: Programming Language :: Python :: 3
Classifier: License :: OSI Approved :: GNU General Public License v3 (GPLv3)
Classifier: Operating System :: OS Independent
Requires-Python: >=3.6
License-File: LICENSE.txt
